transiter_ny_mta/__init__.py
transiter_ny_mta/alertsparser.py
transiter_ny_mta/stationscsvparser.py
transiter_ny_mta/subwaytripsparser.py
transiter_ny_mta/proto/__init__.py
transiter_ny_mta/proto/gtfs_rt_vendorizer.py
transiter_ny_mta/proto/alerts_pb2/__init__.py
transiter_ny_mta/proto/alerts_pb2/transiter_ny_mta_alerts_gtfs_rt_base_pb2.py
transiter_ny_mta/proto/alerts_pb2/transiter_ny_mta_alerts_mta_extension_pb2.py
transiter_ny_mta/proto/alerts_pb2/transiter_ny_mta_alerts_transiter_extension_pb2.py
transiter_ny_mta/proto/subwaytrips_pb2/__init__.py
transiter_ny_mta/proto/subwaytrips_pb2/transiter_ny_mta_subwaytrips_gtfs_rt_base_pb2.py
transiter_ny_mta/proto/subwaytrips_pb2/transiter_ny_mta_subwaytrips_mta_extension_pb2.py
transiter_ny_mta/proto/subwaytrips_pb2/transiter_ny_mta_subwaytrips_transiter_extension_pb2.py
transiter_ny_mta-0.1.0.dist-info/METADATA
transiter_ny_mta-0.1.0.dist-info/WHEEL
transiter_ny_mta-0.1.0.dist-info/top_level.txt
transiter_ny_mta-0.1.0.dist-info/RECORD
