Metadata-Version: 2.1
Name: transiter-ny-mta
Version: 0.1.0
Summary: Transiter parsers for NY MTA transit systems (subway, LIRR, MetroNorth)
Home-page: https://github.com/jamespfennell/transiter-nycsubway
Author: James Fennell
Author-email: jamespfennell@gmail.com
License: MIT
Platform: UNKNOWN
Requires-Dist: python-dateutil (>=2.8.1)
Requires-Dist: transiter (>=0.5.0)
